bt_data/__init__.py
bt_data/data.py
bt_data/db/DbAdapter.py
bt_data/db/PostgresqlAdapter.py
bt_data/db/__init__.py
bt_data/enum/SyncType.py
bt_data/enum/__init__.py
bt_data/model/AKShareSyncModel.py
bt_data/model/AKShareSyncModelClean.py
bt_data/model/Df.py
bt_data/model/Instrument.py
bt_data/model/SyncModel.py
bt_data/model/SyncModelClean.py
bt_data/model/__init__.py
bt_data/model/akshare/AKShareStockInfoACodeName.py
bt_data/model/akshare/__init__.py
bt_data/test/__init__.py
bt_data/test/test.py
bt_data-0.0.11.dist-info/METADATA
bt_data-0.0.11.dist-info/WHEEL
bt_data-0.0.11.dist-info/top_level.txt
bt_data-0.0.11.dist-info/RECORD
