Metadata-Version: 2.1
Name: bt-data
Version: 0.0.11
Summary: BotTrader Data Package
Home-page: https://dev.azure.com/enfuture/BotTrader/_git/bt-data
Author: heian0224
Author-email: heian0224@gmail.com
License: UNKNOWN
Project-URL: Bug Tracker, https://dev.azure.com/enfuture/BotTrader/_git/bt-data/issues
Platform: UNKNOWN
Classifier: Programming Language :: Python :: 3
Classifier: License :: OSI Approved :: MIT License
Classifier: Operating System :: OS Independent
Requires-Python: >=3.10
Requires-Dist: SQLAlchemy
Requires-Dist: akshare
Requires-Dist: pandas
Requires-Dist: psycopg2-binary
Requires-Dist: sqlalchemy2-stubs
Requires-Dist: sqlmodel
